visionmadeeasy/__init__.py
visionmadeeasy-2019.2.17.dist-info/LICENSE.txt
visionmadeeasy-2019.2.17.dist-info/METADATA
visionmadeeasy-2019.2.17.dist-info/WHEEL
visionmadeeasy-2019.2.17.dist-info/top_level.txt
visionmadeeasy-2019.2.17.dist-info/RECORD
