Metadata-Version: 2.1
Name: visionmadeeasy
Version: 2019.2.17
Summary: A module intended to abstract away a lot of the complexity of using OpenCV to detect and recognise faces for beginner programmers.
Home-page: https://pbaumgarten.com/visionmadeeasy
Author: Paul Baumgarten
Author-email: pbaumgarten@gmail.com
License: UNKNOWN
Keywords: opencv face detection recognition beginner
Platform: UNKNOWN
Classifier: Programming Language :: Python :: 3
Classifier: License :: OSI Approved :: MIT License
Classifier: Operating System :: OS Independent
Requires-Python: >=3
Requires-Dist: opencv-contrib-python
Requires-Dist: numpy
Requires-Dist: Pillow
